{
  "ESM19": {
    "dappConfig": {
      "comment": "expiry: May 15, 2019 4:15pm ET, supportedMove: 0.085 corresponds to 8.5%",
      "expiry": "1557951300",
      "supportedMove": "0.085"
    },
    "uploaderConfig": {
      "publishInterval": "900",
      "minDelay": "600",
      "numerator": {
        "dataSource": "Barchart",
        "assetName": "ESM19"
      }
    }
  },
  "CBN19": {
    "dappConfig": {
      "comment": "expiry: May 15, 2019 7:30pm BST, supportedMove: 0.1 corresponds to 10%",
      "expiry": "1557945000",
      "supportedMove": "0.1"
    },
    "uploaderConfig": {
      "publishInterval": "900",
      "minDelay": "600",
      "numerator": {
        "dataSource": "Barchart",
        "assetName": "CBN19"
      }
    }
  },
  "ZILLOWSFHV": {
    "dappConfig": {
      "comment": "expiry: June 13, 2022 7:00AM GMT, supportedMove: 0.1 corresponds to 10%",
      "expiry": "1655103600",
      "supportedMove": "0.1"
    },
    "uploaderConfig": {
      "publishInterval": "1",
      "minDelay": "1",
      "numerator": {
        "dataSource": "Zillow",
        "assetName": "SF"
      },
      "denominator": {
        "dataSource": "Coinbase",
        "assetName": "ETH-USD"
      }
    }
  }
}
